FTP_manager/__init__.py
FTP_manager/ftp_manager.py
FTP_manager-1.0.0.dist-info/METADATA
FTP_manager-1.0.0.dist-info/WHEEL
FTP_manager-1.0.0.dist-info/top_level.txt
FTP_manager-1.0.0.dist-info/RECORD
