Metadata-Version: 2.1
Name: FTP-manager
Version: 1.0.0
Summary: A Python package for FTP file management.
Home-page: https://github.com/mgutale/FTP_manager
Author: Mo Gutale
Author-email: mgutale@me.com
Classifier: Programming Language :: Python :: 3
Classifier: License :: OSI Approved :: MIT License
Classifier: Operating System :: OS Independent
Requires-Dist: pandas
